{
    "presets": [
{"locale": "qic", "preset_name": "js", "shortName": "JS", "longName": "Jehovapaj Shimi", "modifyTime": 1426257657, "description": "Jehovapaj Shimi (Cotopaxi)"},
{"locale": "es", "preset_name": "nwt1984S", "shortName": "TNM1984", "longName": "Traducci칩n del Nuevo Mundo 1984", "modifyTime": 1390532303, "description": "Traducci칩n del Nuevo Mundo 1984"},
{"locale": "en", "preset_name": "nwt1984E", "shortName": "NWT1984", "longName": "New World Translation 1984", "modifyTime": 1404229477, "description": "New World Translation 1984"},
{"locale": "en", "preset_name": "nwt2013E", "shortName": "NWT2013", "longName": "New World Translation 2013", "modifyTime": 1390532307, "description": "New World Translation 2013"},
{"locale": "no", "preset_name": "nwt1984N", "shortName": "NV1985", "longName": "Ny Verden-Oversettelsen 1984", "modifyTime": 1426391145, "description": "Ny Verden-Oversettelsen 1984"},
{"locale": "qia", "preset_name": "qca4", "shortName": "QCA4", "longName": "Dios Rimashca Shimi", "modifyTime": 1415247992, "description": "Dios Rimashca Shimi (Ca침ar)"},
{"locale": "shuar", "preset_name": "JIVAIE", "shortName": "JIVAIE", "longName": "NT Shuar", "modifyTime": 1426389153, "description": "AIE NT (Shuar)"}
		],

    "locale_display": {
        "shuar": "Shuar",
        "qix": "Quichua Cotopaxi",
        "qic": "Quichua Chimborazo",
        "qia": "Quichua Ca침ar",
        "ace": "Aceh",
        "alp": "Alune",
        "blz": "Balantak",
        "ban": "Bali",
        "ptu": "Bambam",
        "btd": "Batak-Dairi",
        "btx": "Batak-Karo",
        "bbc": "Batak-Toba",
        "bts": "Batak-Simalungun",
        "bug": "Bugis",
        "nij": "Dayak-Ngaju",
        "mvp": "Duri",
        "gor": "Gorontalo",
        "kje": "Kisar",
        "kzf": "Kaili Da'a",
        "ljp": "Lampung",
        "mad": "Madura",
        "mak": "Makassar",
        "mwv": "Mentawai",
        "min": "Minangkabau",
        "mog": "Mongondow",
        "npy": "Napu",
        "nia": "Nias",
        "zzz-ROTE": "Rote",
        "sxn": "Sangir",
        "sas": "Sasak",
        "tby": "Tabaru",
        "sda": "Toraja",
        "yli": "Yali-Angguruk"
    },

    "download_url_format": "http://qibi.is-a-bookkeeper.com/2/get_yes.php?preset_name=$PRESET_NAME"
}